<Unit Code="XXXX-XX-XXXXXX" ID="IIS-MR-MATH-GRADEXX-XXXXXX">
	<Body>
		<Sent idx="1">
	(LF0
		(s1w2 have)
		(s1w1 Sarah)
		(s1w4 box)
		(s1w3 7)
		(s1w6 apple)
		(s1w5 of)
	)

	(LF1
		(verb v1 s1w2)
		(nsubj v1 n5)
		(head n5 s1w1)
		(dobj v1 n1)
		(head n1 s1w4)
		(nummod n1 s1w3)
		(nmod n1 n7)
		(head n7 s1w6)
		(case n7 s1w5)
	)

	(LF2
		(= (quan q1 # s1w4) 7)(verb q1 s1w2)(role q1 dobj)
		
	)

		</Sent>
		<Sent idx="2">
	(LF0
		(s2w3 hold)
		(s2w2 box)
		(s2w1 each)
		(s2w5 apple)
		(s2w4 7)
	)

	(LF1
		(verb v2 s2w3)
		(nsubj v2 n2)
		(head n2 s2w2)
		(det n2 s2w1)
		(dobj v2 n3)
		(head n3 s2w5)
		(nummod n3 s2w4)
	)

	(LF2
		(= (quan q2 # s2w2) 1)(verb q2 s2w3)(role q2 nsubj)
		(= (quan q3 # s2w5) 7)(verb q3 s2w3)(role q3 dobj)
		(q_map m1 q2 q3)(verb m1 s2w3)
		
	)

		</Sent>
	</Body>
	<Ques idx="1">
		<Sent idx="1">
	(LF0
		(s3w6 have)
		(s3w3 apple)
		(s3w2 many)
		(s3w1 how)
		(s3w4 do)
		(s3w5 Sarah)
	)

	(LF1
		(verb v3 s3w6)
		(dobj v3 n4)
		(head n4 s3w3)
		(amod n4 s3w2)
		(advmod n4 s3w1)
		(aux v3 s3w4)
		(nsubj v3 n11)
		(head n11 s3w5)
	)

	(LF2
		
		(ASK ANS (Multiplication (quan q1 # s1w4) (Get (u_map ?m # s1w4 # s2w5) (COND (verb ?m s2w3)))))
	)

		</Sent>
	</Ques>
</Unit>
