<Unit ID="IIS-MR-MATH-GRADEXX-XXXXXX">
<Traces>
<Trace>
  <CHUNK_TREE>
      <CHUNK>BeginTree</CHUNK>
        <CHUNK>29(child/child)</CHUNK>
          <CHUNK>OP_CommonDiv</CHUNK>
            <CHUNK>58child</CHUNK>
            <CHUNK>UPSCOPE</CHUNK>
            <CHUNK>2child</CHUNK>
            <CHUNK>UPSCOPE</CHUNK>
          <CHUNK>UPSCOPE</CHUNK>
        <CHUNK>UPSCOPE</CHUNK>
      <CHUNK>EndTree</CHUNK>
  </CHUNK_TREE>
  <math ID='ctx_158'>
    29(child/child)
    CommonDiv
    <math ID='NULL'>
      58child
    </math>
    <math ID='NULL'>
      2child
    </math>
  </math>
  <ctx ID='ctx_155'>
    <__one_line_xml_ASK__ANS>29</__one_line_xml_ASK__ANS>
    <ctx ID='ctx_154'>
      ( CLUE::Input ( ASK ANS ( CommonDiv ( quan q1 # s1w2 ) ( quan q2 # s2w4 ) ) ) )
    </ctx>
    <ctx ID='ctx_158'>
      ( CLUE::Util ( CommonDiv 58 2 = 29 ) )
      ( CLUE::Util ( Val1 ( m_real 58 ) ( m_fact ( quan q1 # s1w2 ) ( 58 ) ) ) )
      ( CLUE::Util ( Val2 ( m_real 2 ) ( m_fact ( quan q2 # s1w2 ) ( 2 ) ) ) )
      <ctx ID='ctx_79'>
        ( CLUE::EVAL::LF2 ( = ( quan q1 # s1w2 ) 58 ) )
        ( CLUE::EVAL::LF2 ( = ( quan q1 # s1w2 ) 58 ) )
        ( CLUE::Create-Fact ( quan q1 # s1w2 ) ( 58 ) )
        <ctx ID='ctx_78'>
          ( CLUE::Input ( = ( quan q1 # s1w2 ) 58 ) )
        </ctx>
      </ctx>
      <ctx ID='ctx_114'>
        ( CLUE::EVAL::LF2 ( = ( quan q2 # s1w2 ) 2 ) )
        ( CLUE::EVAL::LF2 ( = ( quan q2 # s1w2 ) 2 ) )
        ( CLUE::Create-Fact ( quan q2 # s1w2 ) ( 2 ) )
        <ctx ID='ctx_113'>
          ( CLUE::Input ( = ( quan q2 # s2w4 ) 2 ) )
        </ctx>
      </ctx>
    </ctx>
  </ctx>
</Trace>
</Traces>
</Unit>
