<?xml version="1.0" encoding="UTF-8"?>
<MRconverter version="0.x">
<ProcStatus code="0">Success</ProcStatus>
<Phase name="logical_from">
<Unit Code="XXXX-XX-XXXXXX" ID="IIS-MR-MATH-GRADEXX-XXXXXX">
<UnitCand accScore="0.0" idx="1" inCandIdx="1" localScore="0.0">
	<Body>
		<Sent idx="1">

<Cand accScore="0.0" idx="1" inCandIdx="1" localScore="0.0">
	<SemRep>{have(5):nsubj={town(2):det={the(1)},nmod={[x1]Milburg(4):case={of(3)}}},dobj={grown-up(7):nummod={5256(6)},cc={and(8)},conj={child(10):nummod={2987(9)}}}}</SemRep>
	<WordList>
		<Word idx="1">the(1,DT): {The}</Word>
		<Word idx="2">town(2,NN): {town}</Word>
		<Word idx="3">of(3,IN): {of}</Word>
		<Word idx="4">Milburg(4,NNP): {Milburg}</Word>
		<Word idx="5">have(5,VBZ): {has}</Word>
		<Word idx="6">5256(6,CD): {5256}</Word>
		<Word idx="7">grown-up(7,NNS): {grown-ups}</Word>
		<Word idx="8">and(8,CC): {and}</Word>
		<Word idx="9">2987(9,CD): {2987}</Word>
		<Word idx="10">child(10,NNS): {children}</Word>
	</WordList>
</Cand>

		</Sent>
	</Body>
	<Ques idx="1">
		<Sent idx="1">

<Cand accScore="0.0" idx="1" inCandIdx="1" localScore="0.0">
	<SemRep>{live(4):nsubj={people(3):amod={many(2):advmod={how(1)}}},nmod={[x1]Milburg(6):case={in(5)}}}</SemRep>
	<WordList>
		<Word idx="1">how(1,WRB): {How}</Word>
		<Word idx="2">many(2,JJ): {many}</Word>
		<Word idx="3">people(3,NNS): {people}</Word>
		<Word idx="4">live(4,VBP): {live}</Word>
		<Word idx="5">in(5,IN): {in}</Word>
		<Word idx="6">Milburg(6,NNP): {Milburg}</Word>
	</WordList>
</Cand>

		</Sent>
	</Ques>
</UnitCand>
</Unit>
</Phase>
</MRconverter>
