<?xml version="1.0" encoding="UTF-8"?>
<MRconverter version="0.x">
<ProcStatus code="0">Success</ProcStatus>
<Phase name="logical_from">
<Unit Code="XXXX-XX-XXXXXX" ID="IIS-MR-MATH-GRADEXX-XXXXXX">
<UnitCand accScore="0.0" idx="1" inCandIdx="1" localScore="0.0">
	<Body>
		<Sent idx="1">

<Cand accScore="0.0" idx="1" inCandIdx="1" localScore="0.0">
	<SemRep>{Arthur(1):dep={[x1]muffin(4):amod={baked(2)},nummod={35(3)}}}</SemRep>
	<WordList>
		<Word idx="1">Arthur(1,NNP): {Arthur}</Word>
		<Word idx="2">baked(2,JJ): {baked}</Word>
		<Word idx="3">35(3,CD): {35}</Word>
		<Word idx="4">muffin(4,NNS): {muffins}</Word>
	</WordList>
</Cand>

		</Sent>
	</Body>
	<Ques idx="1">
		<Sent idx="1">

<Cand accScore="0.0" idx="1" inCandIdx="1" localScore="0.0">
	<SemRep>{have(7):dep={more(3):amod={many(2):advmod={how(1)}},dep={muffin(4)}},aux={do(5)},nsubj={Arthur(6)},xcomp={bake(9):mark={to(8)},xcomp={have(11):mark={to(10)},dobj={[x1]muffin(13):nummod={83(12)}}}}}</SemRep>
	<WordList>
		<Word idx="1">how(1,WRB): {How}</Word>
		<Word idx="2">many(2,JJ): {many}</Word>
		<Word idx="3">more(3,JJR): {more}</Word>
		<Word idx="4">muffin(4,NNS): {muffins}</Word>
		<Word idx="5">do(5,VBZ): {does}</Word>
		<Word idx="6">Arthur(6,NNP): {Arthur}</Word>
		<Word idx="7">have(7,VB): {have}</Word>
		<Word idx="8">to(8,TO): {to}</Word>
		<Word idx="9">bake(9,VB): {bake}</Word>
		<Word idx="10">to(10,TO): {to}</Word>
		<Word idx="11">have(11,VB): {have}</Word>
		<Word idx="12">83(12,CD): {83}</Word>
		<Word idx="13">muffin(13,NNS): {muffins}</Word>
	</WordList>
</Cand>

		</Sent>
	</Ques>
</UnitCand>
</Unit>
</Phase>
</MRconverter>
