<?xml version="1.0" encoding="UTF-8"?>
<MRconverter version="0.x">
<ProcStatus code="0">Success</ProcStatus>
<Phase name="logical_from">
<Unit Code="XXXX-XX-XXXXXX" ID="IIS-MR-MATH-GRADEXX-XXXXXX">
<UnitCand accScore="0.0" idx="1" inCandIdx="1" localScore="0.0">
	<Body>
		<Sent idx="1">

<Cand accScore="0.0" idx="1" inCandIdx="1" localScore="0.0">
	<SemRep>{fill(4):nsubjpass={[x1]ship(2):det={a(1)}},auxpass={be(3)},nmod={ton(7):case={with(5)},nummod={5973(6)},nmod={cargo(9):case={of(8)}}}}</SemRep>
	<WordList>
		<Word idx="1">a(1,DT): {A}</Word>
		<Word idx="2">ship(2,NN): {ship}</Word>
		<Word idx="3">be(3,VBZ): {is}</Word>
		<Word idx="4">fill(4,VBN): {filled}</Word>
		<Word idx="5">with(5,IN): {with}</Word>
		<Word idx="6">5973(6,CD): {5973}</Word>
		<Word idx="7">ton(7,NNS): {tons}</Word>
		<Word idx="8">of(8,IN): {of}</Word>
		<Word idx="9">cargo(9,NN): {cargo}</Word>
	</WordList>
</Cand>

		</Sent>
		<Sent idx="2">

<Cand accScore="0.0" idx="1" inCandIdx="1" localScore="0.0">
	<SemRep>{stop(2):nsubj={[x1]it(1)},nmod={Bahamas(5):case={in(3)},det={the(4)}},advcl={load(9):advmod={where(7)},nsubj={sailor(8)},dobj={ton(11):nummod={8723(10)},nmod={onboard(14):case={of(12)},compound={cargo(13)}}}}}</SemRep>
	<WordList>
		<Word idx="1">it(1,PRP): {It}</Word>
		<Word idx="2">stop(2,VBZ): {stops}</Word>
		<Word idx="3">in(3,IN): {in}</Word>
		<Word idx="4">the(4,DT): {the}</Word>
		<Word idx="5">Bahamas(5,NNPS): {Bahamas}</Word>
		<Word idx="6">where(7,WRB): {where}</Word>
		<Word idx="7">sailor(8,NNS): {sailors}</Word>
		<Word idx="8">load(9,VBP): {load}</Word>
		<Word idx="9">8723(10,CD): {8723}</Word>
		<Word idx="10">ton(11,NNS): {tons}</Word>
		<Word idx="11">of(12,IN): {of}</Word>
		<Word idx="12">cargo(13,NN): {cargo}</Word>
		<Word idx="13">onboard(14,NN): {onboard}</Word>
	</WordList>
</Cand>

		</Sent>
	</Body>
	<Ques idx="1">
		<Sent idx="1">

<Cand accScore="0.0" idx="1" inCandIdx="1" localScore="0.0">
	<SemRep>{hold(9):dobj={ton(3):amod={many(2):advmod={how(1)}},nmod={cargo(5):case={of(4)}}},aux={do(6)},nsubj={[x1]ship(8):det={the(7)}},advmod={now(10)}}</SemRep>
	<WordList>
		<Word idx="1">how(1,WRB): {How}</Word>
		<Word idx="2">many(2,JJ): {many}</Word>
		<Word idx="3">ton(3,NNS): {tons}</Word>
		<Word idx="4">of(4,IN): {of}</Word>
		<Word idx="5">cargo(5,NN): {cargo}</Word>
		<Word idx="6">do(6,VBZ): {does}</Word>
		<Word idx="7">the(7,DT): {the}</Word>
		<Word idx="8">ship(8,NN): {ship}</Word>
		<Word idx="9">hold(9,VBP): {hold}</Word>
		<Word idx="10">now(10,RB): {now}</Word>
	</WordList>
</Cand>

		</Sent>
	</Ques>
	<SolType>
		<Cand accScore="0.0" idx="1" localScore="0.0">Addition</Cand>
	</SolType>
</UnitCand>
</Unit>
</Phase>
</MRconverter>
